pipenv_pipes/__init__.py
pipenv_pipes/cli.py
pipenv_pipes/core.py
pipenv_pipes/environment.py
pipenv_pipes/pipenv.py
pipenv_pipes/utils.py
pipenv_pipes/picker/__init__.py
pipenv_pipes/picker/colors.py
pipenv_pipes/picker/elements.py
pipenv_pipes/picker/keys.py
pipenv_pipes-0.7.1.dist-info/METADATA
pipenv_pipes-0.7.1.dist-info/PKG-INFO (DESKTOP-ANVFKAH's conflicted copy 2018-06-09)
pipenv_pipes-0.7.1.dist-info/RECORD
pipenv_pipes-0.7.1.dist-info/WHEEL
pipenv_pipes-0.7.1.dist-info/dependency_links (DESKTOP-ANVFKAH's conflicted copy 2018-06-09).txt
pipenv_pipes-0.7.1.dist-info/entry_points.txt
pipenv_pipes-0.7.1.dist-info/top_level.txt
