Metadata-Version: 2.1
Name: pipenv-pipes
Version: 0.7.1
Summary: CLI Tool to help manage Pipenv Enviroments and corresponding Project Directories.
Home-page: https://github.com/gtalarico/pipenv-pipes
Author: Gui Talarico
Author-email: gui.talarico+pip@gmail.com
License: MIT license
Keywords: pipenv_pipes
Platform: UNKNOWN
Classifier: Development Status :: 4 - Beta
Classifier: Intended Audience :: Developers
Classifier: License :: OSI Approved :: MIT License
Classifier: Natural Language :: English
Classifier: Programming Language :: Python :: 3
Classifier: Programming Language :: Python :: 3.4
Classifier: Programming Language :: Python :: 3.5
Classifier: Programming Language :: Python :: 3.6
Requires-Dist: Click (>=6.0)
Requires-Dist: colorama (>=0.3)
